{
  "name": "ProjectNest Dark",
  "type": "dark",
  "colors": {
    "background": "hsl(222.2, 84%, 4.9%)",
    "foreground": "hsl(210, 40%, 98%)",
    "card": "hsl(222.2, 84%, 4.9%)",
    "cardForeground": "hsl(210, 40%, 98%)",
    "cardHover": "hsl(217.2, 32.6%, 17.5%)",
    "primary": "hsl(210, 40%, 98%)",
    "primaryForeground": "hsl(222.2, 47.4%, 11.2%)",
    "primaryHover": "hsl(210, 40%, 90%)",
    "secondary": "hsl(217.2, 32.6%, 17.5%)",
    "secondaryForeground": "hsl(210, 40%, 98%)",
    "secondaryHover": "hsl(217.2, 32.6%, 25%)",
    "muted": "hsl(217.2, 32.6%, 17.5%)",
    "mutedForeground": "hsl(215, 20.2%, 65.1%)",
    "accent": "hsl(217.2, 32.6%, 17.5%)",
    "accentForeground": "hsl(210, 40%, 98%)",
    "destructive": "hsl(0, 62.8%, 30.6%)",
    "destructiveForeground": "hsl(210, 40%, 98%)",
    "success": "hsl(120, 50%, 35%)",
    "warning": "hsl(45, 90%, 50%)",
    "border": "hsl(217.2, 32.6%, 17.5%)",
    "borderLight": "hsl(217.2, 32.6%, 25%)",
    "input": "hsl(217.2, 32.6%, 17.5%)",
    "ring": "hsl(212.7, 26.8%, 83.9%)",
    "popover": "hsl(222.2, 47.4%, 11.2%)",
    "popoverForeground": "hsl(210, 40%, 98%)",
    "sidebarBackground": "hsl(240, 5.9%, 10%)",
    "sidebarForeground": "hsl(240, 4.8%, 95.9%)",
    "sidebarPrimary": "hsl(224.3, 76.3%, 48%)",
    "sidebarPrimaryForeground": "hsl(0, 0%, 100%)",
    "sidebarAccent": "hsl(240, 3.7%, 15.9%)",
    "sidebarAccentForeground": "hsl(240, 4.8%, 95.9%)",
    "sidebarBorder": "hsl(240, 3.7%, 15.9%)",
    "sidebarRing": "hsl(217.2, 91.2%, 59.8%)"
  },
  "properties": {
    "radius": "0.5rem",
    "radiusSm": "0.25rem",
    "radiusLg": "0.75rem",
    "shadowSm": "0 1px 2px 0 rgb(0 0 0 / 0.15)",
    "shadowMd": "0 4px 6px -1px rgb(0 0 0 / 0.3), 0 2px 4px -2px rgb(0 0 0 / 0.2)",
    "shadowLg": "0 10px 15px -3px rgb(0 0 0 / 0.3), 0 4px 6px -4px rgb(0 0 0 / 0.2)"
  }
}